{
    "app": {
        "name": "Cards for Humanity - Development"
    },
    "facebook": {
        "clientID": "APP_ID",
        "clientSecret": "APP_SECRET",
        "callbackURL": "https://izanami-cfh-staging-pr-12.herokuapp.com/auth/facebook"
    },
    "twitter": {
        "clientID": "CONSUMER_KEY",
        "clientSecret": "CONSUMER_SECRET",
        "callbackURL": "https://izanami-cfh-staging-pr-12.herokuapp.com/auth/twitter"
    },
    "github": {
        "clientID": "APP_ID",
        "clientSecret": "APP_SECRET",
        "callbackURL": "https://izanami-cfh-staging-pr-12.herokuapp.com/auth/github"
    },
    "google": {
        "clientID": "APP_ID",
        "clientSecret": "APP_SECRET",
        "callbackURL": "https://izanami-cfh-staging-pr-12.herokuapp.com/auth/google"
    }
}